PlotlyLogo/Blosum62.txt
PlotlyLogo/__init__.py
PlotlyLogo/logo.py
plotly_logo-0.0.2.dist-info/LICENSE
plotly_logo-0.0.2.dist-info/METADATA
plotly_logo-0.0.2.dist-info/WHEEL
plotly_logo-0.0.2.dist-info/top_level.txt
plotly_logo-0.0.2.dist-info/RECORD
