Metadata-Version: 2.1
Name: plotly-logo
Version: 0.0.2
Summary: A Python library for making amino acid sequence logos using the Plotly framework.
Home-page: https://github.com/kevinkovalchik/Plotly-Logo
Author: Kevin Kovalchik
Author-email: 
License: MIT License
Platform: UNKNOWN
Classifier: Programming Language :: Python :: 3
Classifier: License :: OSI Approved :: MIT License
Classifier: Operating System :: OS Independent
Requires-Python: >=3.7
Requires-Dist: numpy
Requires-Dist: plotly (>=1.12.0)
Requires-Dist: pandas
